{
  "123554":{
    "class":"м",
    "type":"jacket",
    "brand":"remain",
    "heading": "Куртка Remain",
    "description": "Very good product for good customer",
    "price": 1499,
    "fabricant":"Китай",
    "color":"Чёрный",
    "size": ["M","L","XL","S","XS"],
    "article":"123554",
    "imgsrc": ["images/1.jpg","images/2.jpg","images/3.jpg","images/4.jpg"]
  },
  "product1":{
    "class":"м",
    "type":"jacket",
    "brand":"remain",
    "heading": "Куртка Remain",
    "description": "Very good product for good customer",
    "price": 1499,
    "fabricant":"Китай",
    "color":"Чёрный",
    "size": ["M","L","XL","S","XS"],
    "article":"order232242",
    "imgsrc": ["images/1.jpg","images/2.jpg","images/3.jpg","images/4.jpg"]
  },
  "product2":{
    "class":"м",
    "type":"jacket",
    "brand":"remain",
    "heading": "Куртка Remain",
    "description": "Blablabla product for good customer",
    "price": 499,
    "fabricant":"Китай",
    "color":"Чёрный",
    "size": ["M","L","XL","S","XS"],
    "article":"order232242",
    "imgsrc": ["images/5.jpg","images/6.jpg","images/7.jpg","images/8.jpg"]
  },
  "product3":{
    "class":"м",
    "type":"jacket",
    "brand":"remain",
    "heading": "Куртка Remain",
    "description": "Very good blablabla for good blablabla",
    "price": 1099,
    "fabricant":"Китай",
    "color":"Чёрный",
    "size": ["M","L","XL","S","XS"],
    "article":"order232242",
    "imgsrc": ["images/9.jpg","images/10.jpg","images/11.jpg","images/12.jpg"]
  },
  "product4":{
    "class":"м",
    "type":"vest",
    "brand":"remain",
    "heading": "Жилет Remain",
    "description": "Blablabla product for good customer",
    "price": 499,
    "fabricant":"Китай",
    "color":"Чёрный",
    "size": ["M","L","XL","S","XS"],
    "article":"order232242",
    "imgsrc": ["images/13.jpg","images/14.jpg","images/15.jpg","images/16.jpg"]
  },
  "product5":{
    "class":"м",
    "type":"vest",
    "brand":"remain",
    "heading": "Жилет Remain",
    "description": "Blablabla product for good customer",
    "price": 799,
    "fabricant":"Китай",
    "color":"Чёрный",
    "size": ["M","L","XL","S","XS"],
    "article":"order232242",
    "imgsrc": ["images/17.jpg","images/18.jpg","images/19.jpg","images/20.jpg"]
  },
  "product6":{
    "class":"м",
    "type":"vest",
    "brand":"remain",
    "heading": "Жилет Remain",
    "description": "Blablabla product for good customer",
    "price": 899,
    "fabricant":"Китай",
    "color":"Чёрный",
    "size": ["M","L","XL","S","XS"],
    "article":"order232242",
    "imgsrc": ["images/21.jpg","images/1.jpg","images/2.jpg","images/3.jpg"]
  },
  "product7":{
    "class":"м",
    "type":"downjacket",
    "brand":"remain",
    "heading": "Пуховик Remain",
    "description": "Blablabla product for good customer",
    "price": 1299,
    "fabricant":"Китай",
    "color":"Чёрный",
    "size": ["M","L","XL","S","XS"],
    "article":"order232242",
    "imgsrc": ["images/4.jpg","images/5.jpg","images/6.jpg","images/7.jpg"]
  },
  "product8":{
    "class":"м",
    "type":"downjacket",
    "brand":"remain",
    "heading": "Пуховик Remain",
    "description": "Blablabla product for good customer",
    "price": 399,
    "fabricant":"Китай",
    "color":"Чёрный",
    "size": ["M","L","XL","S","XS"],
    "article":"order232242",
    "imgsrc": ["images/8.jpg","images/9.jpg","images/10.jpg","images/11.jpg"]
  },
  "product9":{
    "class":"м",
    "type":"downjacket",
    "brand":"remain",
    "heading": "Пуховик Remain",
    "description": "Blablabla product for good customer",
    "price": 899,
    "fabricant":"Китай",
    "color":"Чёрный",
    "size": ["M","L","XL","S","XS"],
    "article":"order232242",
    "imgsrc": ["images/12.jpg","images/13.jpg","images/14.jpg","images/15.jpg"]
  },
  "product10":{
    "class":"м",
    "type":"jacket",
    "brand":"remain",
    "heading": "Куртка Remain",
    "description": "Blablabla product for good customer",
    "price": 799,
    "fabricant":"Китай",
    "color":"Чёрный",
    "size": ["M","L","XL","S","XS"],
    "article":"order232242",
    "imgsrc": ["images/16.jpg","images/17.jpg","images/18.jpg","images/19.jpg"]
  },
  "product11":{
    "class":"ж",
    "type":"jacket",
    "brand":"remain",
    "heading": "Куртка Remain",
    "description": "Blablabla product for good customer",
    "price": 799,
    "fabricant":"Китай",
    "color":"Чёрный",
    "size": ["M","L","XL","S","XS"],
    "article":"order232242",
    "imgsrc": ["images/20.jpg","images/21.jpg","images/1.jpg","images/2.jpg"]
  },
  "product12":{
    "class":"ж",
    "type":"jacket",
    "brand":"remain",
    "heading": "Куртка Remain",
    "description": "Blablabla product for good customer",
    "price": 799,
    "fabricant":"Китай",
    "color":"Чёрный",
    "size": ["M","L","XL","S","XS"],
    "article":"order232242",
    "imgsrc": ["images/3.jpg","images/4.jpg","images/5.jpg","images/6.jpg"]
  },
  "product13":{
    "class":"ж",
    "type":"vest",
    "brand":"remain",
    "heading": "Жилет Remain",
    "description": "Blablabla product for good customer",
    "price": 799,
    "fabricant":"Китай",
    "color":"Чёрный",
    "size": ["M","L","XL","S","XS"],
    "article":"order232242",
    "imgsrc": ["images/7.jpg","images/8.jpg","images/9.jpg","images/10.jpg"]
  },
  "product14":{
    "class":"ж",
    "type":"vest",
    "brand":"remain",
    "heading": "Жилет Remain",
    "description": "Blablabla product for good customer",
    "price": 799,
    "fabricant":"Китай",
    "color":"Чёрный",
    "size": ["M","L","XL","S","XS"],
    "article":"order232242",
    "imgsrc": ["images/11.jpg","images/12.jpg","images/13.jpg","images/14.jpg"]
  },
  "product15":{
    "class":"ж",
    "type":"vest",
    "brand":"remain",
    "heading": "Жилет Remain",
    "description": "Blablabla product for good customer",
    "price": 799,
    "fabricant":"Китай",
    "color":"Чёрный",
    "size": ["M","L","XL","S","XS"],
    "article":"order232242",
    "imgsrc": ["images/15.jpg","images/16.jpg","images/17.jpg","images/18.jpg"]
  },
  "product16":{
    "class":"ж",
    "type":"downjacket",
    "brand":"remain",
    "heading": "Пуховик Remain",
    "description": "Blablabla product for good customer",
    "price": 799,
    "fabricant":"Китай",
    "color":"Чёрный",
    "size": ["M","L","XL","S","XS"],
    "article":"order232242",
    "imgsrc": ["images/19.jpg","images/20.jpg","images/21.jpg","images/1.jpg"]
  },
  "product17":{
    "class":"ж",
    "type":"downjacket",
    "brand":"remain",
    "heading": "Пуховик Remain",
    "description": "Blablabla product for good customer",
    "price": 799,
    "fabricant":"Китай",
    "color":"Чёрный",
    "size": ["M","L","XL","S","XS"],
    "article":"order232242",
    "imgsrc": ["images/2.jpg","images/3.jpg","images/4.jpg","images/5.jpg"]
  },
  "product18":{
    "class":"ж",
    "type":"downjacket",
    "brand":"remain",
    "heading": "Пуховик Remain",
    "description": "Blablabla product for good customer",
    "price": 799,
    "fabricant":"Китай",
    "color":"Чёрный",
    "size": ["M","L","XL","S","XS"],
    "article":"order232242",
    "imgsrc": ["images/6.jpg","images/7.jpg","images/8.jpg","images/9.jpg"]
  }
}

